pywiegandpi/__init__.py
pywiegandpi-1.0.1.dist-info/LICENSE
pywiegandpi-1.0.1.dist-info/METADATA
pywiegandpi-1.0.1.dist-info/WHEEL
pywiegandpi-1.0.1.dist-info/top_level.txt
pywiegandpi-1.0.1.dist-info/RECORD
