Metadata-Version: 2.1
Name: pywiegandpi
Version: 1.0.1
Summary: Automatically decode Wiegand data from Raspberry Pi GPIO pins.
Author-email: Jaimyn Mayer <hello@jaimyn.dev>
Project-URL: Homepage, https://github.com/membermatters/pywiegandpi
Project-URL: Issues, https://github.com/membermatters/pywiegandpi/issues
Classifier: Programming Language :: Python :: 3
Classifier: License :: OSI Approved :: MIT License
Classifier: Operating System :: POSIX :: Linux
Requires-Python: >=3.9
License-File: LICENSE
Requires-Dist: pigpio >=1.78
